pdbufr/__init__.py
pdbufr/__main__.py
pdbufr/bufr_read.py
pdbufr/version.py
pdbufr/core/accessor.py
pdbufr/core/filters.py
pdbufr/core/keys.py
pdbufr/core/param.py
pdbufr/core/structure.py
pdbufr/core/subset.py
pdbufr/high_level_bufr/__init__.py
pdbufr/high_level_bufr/bufr.py
pdbufr/high_level_bufr/codesfile.py
pdbufr/high_level_bufr/codesmessage.py
pdbufr/readers/__init__.py
pdbufr/readers/custom.py
pdbufr/readers/flat.py
pdbufr/readers/generic.py
pdbufr/readers/geopot.py
pdbufr/readers/station.py
pdbufr/readers/synop.py
pdbufr/readers/temp.py
pdbufr/utils/convert.py
pdbufr/utils/exception.py
pdbufr/utils/testing.py
pdbufr/utils/units.py
pdbufr-0.14.1.dist-info/licenses/LICENSE
pdbufr-0.14.1.dist-info/METADATA
pdbufr-0.14.1.dist-info/WHEEL
pdbufr-0.14.1.dist-info/top_level.txt
pdbufr-0.14.1.dist-info/RECORD
